mmft.hybridsim-0.1.1.dist-info/LICENSE
mmft.hybridsim-0.1.1.dist-info/top_level.txt
mmft.hybridsim-0.1.1.dist-info/WHEEL
mmft.hybridsim-0.1.1.dist-info/METADATA
mmft.hybridsim-0.1.1.dist-info/RECORD
mmft/hybridsim/CMakeLists.txt
mmft/hybridsim/pyhybridsim.cpython-311-x86_64-linux-gnu.so
mmft/hybridsim/__init__.py
mmft/hybridsim/bindings.cpp
