Metadata-Version: 2.1
Name: mmft.hybridsim
Version: 0.1.1
Summary: A hybrid simulator for closed channel-based microfluidic devices
Author-email: Michel Takken <michel.takken@tum.de>
License: GNU GENERAL PUBLIC LICENSE
Keywords: MMFT,microfluidics,design automation,hybrid simulation
Classifier: Development Status :: 3 - Alpha
Classifier: Programming Language :: Python :: 3
Classifier: Programming Language :: Python :: 3.8
Classifier: Programming Language :: Python :: 3.9
Classifier: Programming Language :: Python :: 3.10
Classifier: Programming Language :: Python :: 3.11
Classifier: Programming Language :: C++
Classifier: License :: OSI Approved :: GNU General Public License v3 (GPLv3)
Classifier: Operating System :: MacOS
Classifier: Operating System :: POSIX :: Linux
Classifier: Intended Audience :: Science/Research
Classifier: Natural Language :: English
Classifier: Topic :: Scientific/Engineering :: Electronic Design Automation (EDA)
Requires-Python: >=3.8
License-File: LICENSE
